CHANGES.txt
README.txt
bootstrap.py
buildout.cfg
deploy.ini.in
setup.py
src/pwt/__init__.py
src/pwt.closure.egg-info/PKG-INFO
src/pwt.closure.egg-info/SOURCES.txt
src/pwt.closure.egg-info/dependency_links.txt
src/pwt.closure.egg-info/entry_points.txt
src/pwt.closure.egg-info/namespace_packages.txt
src/pwt.closure.egg-info/not-zip-safe
src/pwt.closure.egg-info/requires.txt
src/pwt.closure.egg-info/top_level.txt
src/pwt/closure/README.txt
src/pwt/closure/__init__.py
src/pwt/closure/cli.py
src/pwt/closure/compile_raw
src/pwt/closure/config1.json
src/pwt/closure/files.py
src/pwt/closure/jinja.py
src/pwt/closure/recipe.py
src/pwt/closure/simple.soy
src/pwt/closure/soyutils.js
src/pwt/closure/soyutils_usegoog.js
src/pwt/closure/test.html
src/pwt/closure/test1.js
src/pwt/closure/test1.soy
src/pwt/closure/test2.js
src/pwt/closure/test_deps1.js
src/pwt/closure/tests.py
src/pwt/closure/wsgi.py
src/pwt/closure/build/closurebuilder.py
src/pwt/closure/build/depstree.py
src/pwt/closure/build/depstree_test.py
src/pwt/closure/build/depswriter.py
src/pwt/closure/build/jscompiler.py
src/pwt/closure/build/source.py
src/pwt/closure/build/source_test.py
src/pwt/closure/build/treescan.py
src/pwt/closure/jars/SoyToJsSrcCompiler.jar
src/pwt/closure/jars/compiler.jar