Metadata-Version: 1.0
Name: pwt.closure
Version: 0.2
Summary: 
